pypatchergba/__init__.py
pypatchergba/cli.py
pypatchergba/patcher.py
pypatchergba-0.1.1.dist-info/LICENSE
pypatchergba-0.1.1.dist-info/METADATA
pypatchergba-0.1.1.dist-info/WHEEL
pypatchergba-0.1.1.dist-info/entry_points.txt
pypatchergba-0.1.1.dist-info/top_level.txt
pypatchergba-0.1.1.dist-info/RECORD
