Metadata-Version: 2.1
Name: pypatchergba
Version: 0.1.1
Summary: A simple Python library to apply IPS, UPS, and BPS ROM patches.
Author-email: James Arrowsmith <jmsarrowsmith05@gmail.com>
License: Apache License
Project-URL: Homepage, https://github.com/jarrowsmith123/PyPatcherGBA
Project-URL: Issues, https://github.com/jarrowsmith123/PyPatcherGBA/issues
Classifier: Development Status :: 4 - Beta
Classifier: Programming Language :: Python :: 3
Classifier: License :: OSI Approved :: Apache Software License
Classifier: Operating System :: OS Independent
Classifier: Topic :: Software Development :: Libraries :: Python Modules
Classifier: Topic :: Games/Entertainment
Requires-Python: >=3.7
License-File: LICENSE
